jarvisplot/__init__.py
jarvisplot/cli.py
jarvisplot/client.py
jarvisplot/config.py
jarvisplot/core.py
jarvisplot/data_loader.py
jarvisplot/inner_func.py
jarvisplot/Figure/__init__.py
jarvisplot/Figure/adapters.py
jarvisplot/Figure/data_pipelines.py
jarvisplot/Figure/figure.py
jarvisplot/Figure/helper.py
jarvisplot/Figure/load_data.py
jarvisplot/Figure/cards/std_axes_adapter_config.json
jarvisplot/cards/args.json
jarvisplot/cards/style_preference.json
jarvisplot/cards/a4paper/1x1/ternary.json
jarvisplot/cards/a4paper/2x1/rect.json
jarvisplot/cards/a4paper/2x1/rect5x1.json
jarvisplot/cards/a4paper/2x1/rect_cmap.json
jarvisplot/cards/a4paper/2x1/ternary.json
jarvisplot/cards/a4paper/2x1/ternary_cmap.json
jarvisplot/cards/a4paper/4x1/rect.json
jarvisplot/cards/a4paper/4x1/rect_cmap.json
jarvisplot/cards/a4paper/4x1/ternary.json
jarvisplot/cards/a4paper/4x1/ternary_cmap.json
jarvisplot/cards/colors/colormaps.json
jarvisplot/cards/default/output.json
jarvisplot/cards/gambit/1x1/ternary.json
jarvisplot/cards/gambit/2x1/rect_cmap.json
jarvisplot/cards/gambit/2x1/ternary.json
jarvisplot/cards/gambit/2x1/ternary_cmap.json
jarvisplot/cards/icons/JarvisHEP.png
jarvisplot/cards/icons/gambit.png
jarvisplot/cards/icons/gambit_small.png
jarvisplot/utils/__init__.py
jarvisplot/utils/cmaps.py
jarvisplot/utils/interpolator.py
jarvisplot-1.0.2.dist-info/METADATA
jarvisplot-1.0.2.dist-info/WHEEL
jarvisplot-1.0.2.dist-info/entry_points.txt
jarvisplot-1.0.2.dist-info/top_level.txt
jarvisplot-1.0.2.dist-info/RECORD
