Metadata-Version: 2.4
Name: jarvisplot
Version: 1.0.2
Summary: JarvisPLOT: YAML-driven plotting engine
Requires-Python: >=3.10
Requires-Dist: loguru
Requires-Dist: pyyaml
Requires-Dist: jsonschema
Requires-Dist: numpy
Requires-Dist: pandas
Requires-Dist: matplotlib
